nullaxe/__init__.py
nullaxe/cleaner.py
nullaxe/functions/__init__.py
nullaxe/functions/_clean_column_names.py
nullaxe/functions/_drop_single_value_columns.py
nullaxe/functions/_enforce_data_types.py
nullaxe/functions/_extract_and_clean_numeric.py
nullaxe/functions/_extract_currency.py
nullaxe/functions/_extract_email.py
nullaxe/functions/_extract_phone_numbers.py
nullaxe/functions/_extract_urls.py
nullaxe/functions/_extract_with_regex.py
nullaxe/functions/_flag_for_review.py
nullaxe/functions/_format_for_display.py
nullaxe/functions/_generate_synthetic.py
nullaxe/functions/_handle_outliers.py
nullaxe/functions/_impute_values.py
nullaxe/functions/_infer_gender.py
nullaxe/functions/_infer_types.py
nullaxe/functions/_missing_data.py
nullaxe/functions/_remove_duplicates.py
nullaxe/functions/_remove_html.py
nullaxe/functions/_remove_pii.py
nullaxe/functions/_remove_punctuation.py
nullaxe/functions/_remove_special_characters.py
nullaxe/functions/_remove_stopwords.py
nullaxe/functions/_remove_unwanted_rows_and_cols.py
nullaxe/functions/_replace_text.py
nullaxe/functions/_standardize_booleans.py
nullaxe/functions/_standardize_categorical_values.py
nullaxe/functions/_standardize_units.py
nullaxe/functions/_summarize_missing_data.py
nullaxe/functions/_whitespace.py
nullaxe-0.4.2.dist-info/licenses/LICENSE
nullaxe-0.4.2.dist-info/METADATA
nullaxe-0.4.2.dist-info/WHEEL
nullaxe-0.4.2.dist-info/top_level.txt
nullaxe-0.4.2.dist-info/RECORD
