Metadata-Version: 2.4
Name: nullaxe
Version: 0.4.2
Summary: A data cleaning library for Pandas and Polars DataFrames with a simple, chainable API.
Author-email: John Tocci <john@johntocci.com>
License: MIT License
Project-URL: Homepage, https://github.com/johntocci/nullaxe
Project-URL: Repository, https://github.com/johntocci/nullaxe
Project-URL: Bug Tracker, https://github.com/johntocci/nullaxe/issues
Keywords: data cleaning,pandas,polars,data science,etl,data processing,nullaxe
Classifier: Development Status :: 4 - Beta
Classifier: Programming Language :: Python :: 3
Classifier: Programming Language :: Python :: 3.8
Classifier: Programming Language :: Python :: 3.9
Classifier: Programming Language :: Python :: 3.10
Classifier: Programming Language :: Python :: 3.11
Classifier: License :: OSI Approved :: MIT License
Classifier: Operating System :: OS Independent
Classifier: Intended Audience :: Developers
Classifier: Intended Audience :: Science/Research
Classifier: Topic :: Scientific/Engineering :: Information Analysis
Classifier: Topic :: Software Development :: Libraries :: Python Modules
Requires-Python: >=3.8
License-File: LICENSE
Requires-Dist: pandas>=1.0
Requires-Dist: polars>=0.19
Requires-Dist: nltk>=3.8
Provides-Extra: dev
Requires-Dist: pytest>=7.0; extra == "dev"
Requires-Dist: build>=0.10; extra == "dev"
Requires-Dist: twine>=4.0; extra == "dev"
Dynamic: license-file
